{"tokenNum": 377, "sentenceNum": 29, "lemmaNum": 218, "lemmaRate": 0.5782493368700266, "sentenceLength": 13.0, "allUpperNum": 7, "firstUpperNum": 50, "allUpperRate": 0.01856763925729443, "firstUpperRate": 0.13262599469496023, "declarSentNum": 28, "imperSentNum": 1, "questionNum": 0, "declarSentRate": 0.9655172413793104, "imperSentRate": 0.034482758620689655, "questionRate": 0.0, "accent": true, "saturation": 4.037037037037037, "paragraphNum": 0, "nounNum": 90, "verbNum": 40, "adjNum": 31, "infNum": 4, "partPastNum": 0, "partPresNum": 2, "partFutNum": 0, "transNum": 1, "xNum": 28, "advNum": 38, "properNounNum": 27, "numNum": 2, "conjNum": 18, "punctNum": 77, "pronNum": 22, "relPronNum": 9, "demPronNum": 14, "adposNum": 1, "multiplePunctNum": 6, "phraseNum": 0, "nounRate": 0.23872679045092837, "verbRate": 0.10610079575596817, "adjRate": 0.08222811671087533, "infRate": 0.010610079575596816, "partPastRate": 0.0, "partPresRate": 0.005305039787798408, "partFutRate": 0.0, "transRate": 0.002652519893899204, "xRate": 0.07427055702917772, "advRate": 0.10079575596816977, "properNounRate": 0.07161803713527852, "numRate": 0.005305039787798408, "conjRate": 0.04774535809018567, "punctRate": 0.20424403183023873, "pronRate": 0.058355437665782495, "relPronRate": 0.023872679045092837, "demPronRate": 0.03713527851458886, "adposRate": 0.002652519893899204, "multiplePunctRate": 0.07792207792207792, "partsDensityRate": 3.685185185185185, "contentfulness": 6.862068965517241, "phraseRate": 0.0, "pastTenseNum": 18, "presentTenseNum": 18, "condNum": 1, "impNum": 2, "freqNum": 0, "causNum": 0, "modalNum": 2, "sg1VerbNum": 9, "sg2VerbNum": 0, "sg3VerbNum": 35, "pl1VerbNum": 3, "pl2VerbNum": 0, "pl3VerbNum": 12, "superlatNum": 0, "comparatNum": 1, "specDerivSuffixNum": 0, "pluralNounNum": 18, "pastTenseRate": 0.45, "presentTenseRate": 0.45, "condRate": 0.025, "impRate": 0.05, "freqRate": 0.0, "causRate": 0.0, "modalRate": 0.05, "sg1VerbRate": 0.225, "sg2VerbRate": 0.0, "sg3VerbRate": 0.875, "pl1VerbRate": 0.075, "pl2VerbRate": 0.0, "pl3VerbRate": 0.3, "superlatRate": 0.0, "comparatRate": 0.03225806451612903, "specDerivSuffixRate": 0.0, "pluralNounRate": 0.2, "subjNum": 26, "objNum": 8, "attNum": 20, "subordNum": 14, "adverbNum": 39, "coordNum": 20, "clauseNum": 54, "simpleNum": 15, "complexNum": 14, "complexity1Num": 8, "complexity2Num": 3, "complexity3Num": 2, "compoundNum": 0, "subjRate": 0.06896551724137931, "objRate": 0.021220159151193633, "attRate": 0.05305039787798409, "subordRate": 0.03713527851458886, "adverbRate": 0.10344827586206896, "coordRate": 0.05305039787798409, "partsRate": 2.0925925925925926, "clauseRate": 1.8620689655172413, "simpleRate": 0.5172413793103449, "complexRate": 0.4827586206896552, "complexity1Rate": 0.27586206896551724, "complexity2Rate": 0.10344827586206896, "complexity3Rate": 0.06896551724137931, "complexClauseRate": 2.7857142857142856, "sentencesPerParagraph": 0.0, "wordsLengthRate": 5.66, "compoundRate": 0.0, "positiveNum": 0, "negativeNum": 0, "precoPositiveNum": 0, "precoNegativeNum": 0, "negemoNum": 0, "negationNum": 8, "functionNum": 178, "contentNum": 199, "vulgarNum": 0, "racistNum": 0, "specStyleNum": 0, "addressingNum": 0, "closingNum": 0, "postscriptNum": 0, "brutalNum": 0, "positiveRate": 0.0, "negativeRate": 0.0, "precoPositiveRate": 0.0, "precoNegativeRate": 0.0, "negemoRate": 0.0, "negationRate": 0.021220159151193633, "functionRate": 0.47214854111405835, "contentRate": 0.5278514588859416, "vulgarRate": 0.0, "racistRate": 0.0, "specStyleRate": 0.0, "addressingRate": 0.0, "closingRate": 0.0, "postscriptRate": 0.0, "brutalRate": 0.0, "epistemicNum": 0, "investNum": 0, "conditionNum": 0, "weaselNum": 0, "peacockNum": 0, "hedgeNum": 0, "doxasticNum": 0, "epistemicRate": 0.0, "investRate": 0.0, "conditionRate": 0.0, "weaselRate": 0.0, "peacockRate": 0.0, "hedgeRate": 0.0, "doxasticRate": 0.0, "loveNum": 0, "anxietyNum": 0, "sorrowNum": 0, "joyNum": 0, "disgustNum": 0, "fearNum": 0, "surpriseNum": 0, "angerNum": 0, "loveRate": 0.0, "anxietyRate": 0.0, "sorrowRate": 0.0, "joyRate": 0.0, "disgustRate": 0.0, "fearRate": 0.0, "surpriseRate": 0.0, "angerRate": 0.0, "slangBeGeneralNum": 0, "slangBeCigaretteNum": 0, "slangBeHumanNum": 0, "slangBeVehicleNum": 0, "slangBeDrugNum": 0, "slangBvNum": 0, "slangBeGeneralRate": 0.0, "slangBeCigaretteRate": 0.0, "slangBeHumanRate": 0.0, "slangBeVehicleRate": 0.0, "slangBeDrugRate": 0.0, "slangBvRate": 0.0, "speechactNum": 0, "quoteNum": 0, "dashNum": 0, "publicNum": 0, "privateNum": 0, "suasiveNum": 0, "discMarkerNum": 0, "smileyNum": 0, "dateNum": 0, "hesitationNum": 0, "restartNum": 0, "repeatNum": 7, "conjBeforeDiscNum": 0, "conjAfterDiscNum": 0, "wordBeforeHesitationNum": 0, "wordAfterHesitationNum": 0, "otherCollocationNum": 0, "speechactRate": 0.0, "quoteRate": 0.0, "dashRate": 0.0, "publicRate": 0.0, "privateRate": 0.0, "suasiveRate": 0.0, "discMarkerRate": 0.0, "smileyRate": 0.0, "dateRate": 0.0, "hesitationRate": 0.0, "restartRate": 0.0, "repeatRate": 0.01856763925729443, "conjBeforeDiscRate": 0.0, "conjAfterDiscRate": 0.0, "wordBeforeHesitationRate": 0.0, "wordAfterHesitationRate": 0.0, "otherCollocationRate": 0.0, "easyWordNum": 345, "hardWordNum": 32, "easyWordRate": 0.9151193633952255, "hardWordRate": 0.08488063660477453, "fleschReadingEaseScore": 67.97421750663132, "gunningFogIndex": 5.23395225464191, "fleschKincaidGradeLevel": 7.007851458885945, "colemanLiauIndex": 11.681228116710876, "smogIndex": 9.029198982220553, "automatedReadabilityIndex": 7.045835543766579, "linsearWriteIndex": 0.8933504070246046, "author": "", "locationNameNum": 0, "locationNameRate": 0.0, "personNameNum": 15, "personNameRate": 0.03978779840848806, "organizationNameNum": 0, "organizationNameRate": 0.0, "misspelledNum": 12, "misspelledRate": 0.03183023872679045, "missingAccentNum": 1, "missingAccentRate": 0.002652519893899204, "foreignAccentNum": 0, "foreignAccentRate": 0.0, "wordConcatNum": 2, "wordConcatRate": 0.005305039787798408, "jLyMistakeNum": 1, "jLyMistakeRate": 0.002652519893899204, "freqSuffixNum": 0, "partsNum": 113, "privateVNum": 0, "publicVNum": 0, "clauseWordNum": 54}