{"tokenNum": 376, "sentenceNum": 29, "lemmaNum": 186, "lemmaRate": 0.4946808510638298, "sentenceLength": 12.96551724137931, "allUpperNum": 0, "firstUpperNum": 33, "allUpperRate": 0.0, "firstUpperRate": 0.08776595744680851, "declarSentNum": 29, "imperSentNum": 0, "questionNum": 0, "declarSentRate": 1.0, "imperSentRate": 0.0, "questionRate": 0.0, "accent": true, "saturation": 3.206896551724138, "paragraphNum": 0, "nounNum": 71, "verbNum": 55, "adjNum": 29, "infNum": 9, "partPastNum": 1, "partPresNum": 5, "partFutNum": 0, "transNum": 1, "xNum": 27, "advNum": 50, "properNounNum": 5, "numNum": 2, "conjNum": 23, "punctNum": 59, "pronNum": 25, "relPronNum": 3, "demPronNum": 11, "adposNum": 2, "multiplePunctNum": 1, "phraseNum": 0, "nounRate": 0.18882978723404256, "verbRate": 0.14627659574468085, "adjRate": 0.07712765957446809, "infRate": 0.023936170212765957, "partPastRate": 0.0026595744680851063, "partPresRate": 0.013297872340425532, "partFutRate": 0.0, "transRate": 0.0026595744680851063, "xRate": 0.07180851063829788, "advRate": 0.13297872340425532, "properNounRate": 0.013297872340425532, "numRate": 0.005319148936170213, "conjRate": 0.061170212765957445, "punctRate": 0.15691489361702127, "pronRate": 0.06648936170212766, "relPronRate": 0.007978723404255319, "demPronRate": 0.02925531914893617, "adposRate": 0.005319148936170213, "multiplePunctRate": 0.01694915254237288, "partsDensityRate": 3.5344827586206895, "contentfulness": 7.068965517241379, "phraseRate": 0.0, "pastTenseNum": 1, "presentTenseNum": 45, "condNum": 2, "impNum": 4, "freqNum": 0, "causNum": 0, "modalNum": 1, "sg1VerbNum": 14, "sg2VerbNum": 0, "sg3VerbNum": 47, "pl1VerbNum": 3, "pl2VerbNum": 3, "pl3VerbNum": 5, "superlatNum": 0, "comparatNum": 0, "specDerivSuffixNum": 0, "pluralNounNum": 7, "pastTenseRate": 0.01818181818181818, "presentTenseRate": 0.8181818181818182, "condRate": 0.03636363636363636, "impRate": 0.07272727272727272, "freqRate": 0.0, "causRate": 0.0, "modalRate": 0.01818181818181818, "sg1VerbRate": 0.2545454545454545, "sg2VerbRate": 0.0, "sg3VerbRate": 0.8545454545454545, "pl1VerbRate": 0.05454545454545454, "pl2VerbRate": 0.05454545454545454, "pl3VerbRate": 0.09090909090909091, "superlatRate": 0.0, "comparatRate": 0.0, "specDerivSuffixRate": 0.0, "pluralNounRate": 0.09859154929577464, "subjNum": 28, "objNum": 23, "attNum": 16, "subordNum": 13, "adverbNum": 56, "coordNum": 19, "clauseNum": 58, "simpleNum": 14, "complexNum": 15, "complexity1Num": 9, "complexity2Num": 3, "complexity3Num": 0, "compoundNum": 0, "subjRate": 0.07446808510638298, "objRate": 0.061170212765957445, "attRate": 0.0425531914893617, "subordRate": 0.034574468085106384, "adverbRate": 0.14893617021276595, "coordRate": 0.05053191489361702, "partsRate": 2.4482758620689653, "clauseRate": 2.0, "simpleRate": 0.4827586206896552, "complexRate": 0.5172413793103449, "complexity1Rate": 0.3103448275862069, "complexity2Rate": 0.10344827586206896, "complexity3Rate": 0.0, "complexClauseRate": 2.933333333333333, "sentencesPerParagraph": 0.0, "wordsLengthRate": 5.280757097791798, "compoundRate": 0.0, "positiveNum": 0, "negativeNum": 0, "precoPositiveNum": 0, "precoNegativeNum": 0, "negemoNum": 0, "negationNum": 14, "functionNum": 171, "contentNum": 205, "vulgarNum": 0, "racistNum": 0, "specStyleNum": 0, "addressingNum": 0, "closingNum": 0, "postscriptNum": 0, "brutalNum": 0, "positiveRate": 0.0, "negativeRate": 0.0, "precoPositiveRate": 0.0, "precoNegativeRate": 0.0, "negemoRate": 0.0, "negationRate": 0.03723404255319149, "functionRate": 0.45478723404255317, "contentRate": 0.5452127659574468, "vulgarRate": 0.0, "racistRate": 0.0, "specStyleRate": 0.0, "addressingRate": 0.0, "closingRate": 0.0, "postscriptRate": 0.0, "brutalRate": 0.0, "epistemicNum": 0, "investNum": 0, "conditionNum": 0, "weaselNum": 0, "peacockNum": 0, "hedgeNum": 0, "doxasticNum": 0, "epistemicRate": 0.0, "investRate": 0.0, "conditionRate": 0.0, "weaselRate": 0.0, "peacockRate": 0.0, "hedgeRate": 0.0, "doxasticRate": 0.0, "loveNum": 0, "anxietyNum": 0, "sorrowNum": 0, "joyNum": 0, "disgustNum": 0, "fearNum": 0, "surpriseNum": 0, "angerNum": 0, "loveRate": 0.0, "anxietyRate": 0.0, "sorrowRate": 0.0, "joyRate": 0.0, "disgustRate": 0.0, "fearRate": 0.0, "surpriseRate": 0.0, "angerRate": 0.0, "slangBeGeneralNum": 0, "slangBeCigaretteNum": 0, "slangBeHumanNum": 0, "slangBeVehicleNum": 0, "slangBeDrugNum": 0, "slangBvNum": 0, "slangBeGeneralRate": 0.0, "slangBeCigaretteRate": 0.0, "slangBeHumanRate": 0.0, "slangBeVehicleRate": 0.0, "slangBeDrugRate": 0.0, "slangBvRate": 0.0, "speechactNum": 0, "quoteNum": 0, "dashNum": 0, "publicNum": 0, "privateNum": 0, "suasiveNum": 0, "discMarkerNum": 0, "smileyNum": 0, "dateNum": 3, "hesitationNum": 0, "restartNum": 0, "repeatNum": 0, "conjBeforeDiscNum": 0, "conjAfterDiscNum": 0, "wordBeforeHesitationNum": 0, "wordAfterHesitationNum": 0, "otherCollocationNum": 0, "speechactRate": 0.0, "quoteRate": 0.0, "dashRate": 0.0, "publicRate": 0.0, "privateRate": 0.0, "suasiveRate": 0.0, "discMarkerRate": 0.0, "smileyRate": 0.0, "dateRate": 0.007978723404255319, "hesitationRate": 0.0, "restartRate": 0.0, "repeatRate": 0.0, "conjBeforeDiscRate": 0.0, "conjAfterDiscRate": 0.0, "wordBeforeHesitationRate": 0.0, "wordAfterHesitationRate": 0.0, "otherCollocationRate": 0.0, "easyWordNum": 355, "hardWordNum": 21, "easyWordRate": 0.9441489361702128, "hardWordRate": 0.05585106382978723, "fleschReadingEaseScore": 68.35000000000002, "gunningFogIndex": 5.208547322083639, "fleschKincaidGradeLevel": 6.946870873074101, "colemanLiauIndex": 10.97107180851064, "smogIndex": 7.908726449838941, "automatedReadabilityIndex": 6.460710748349232, "linsearWriteIndex": 0.7929200293470284, "author": "", "locationNameNum": 0, "locationNameRate": 0.0, "personNameNum": 2, "personNameRate": 0.005319148936170213, "organizationNameNum": 0, "organizationNameRate": 0.0, "misspelledNum": 1, "misspelledRate": 0.0026595744680851063, "missingAccentNum": 0, "missingAccentRate": 0.0, "foreignAccentNum": 0, "foreignAccentRate": 0.0, "wordConcatNum": 0, "wordConcatRate": 0.0, "jLyMistakeNum": 0, "jLyMistakeRate": 0.0, "freqSuffixNum": 0, "partsNum": 142, "privateVNum": 0, "publicVNum": 0, "clauseWordNum": 58}