{"tokenNum": 1188, "sentenceNum": 65, "lemmaNum": 434, "lemmaRate": 0.3653198653198653, "sentenceLength": 18.276923076923076, "allUpperNum": 1, "firstUpperNum": 108, "allUpperRate": 0.0008417508417508417, "firstUpperRate": 0.09090909090909091, "declarSentNum": 64, "imperSentNum": 0, "questionNum": 1, "declarSentRate": 0.9846153846153847, "imperSentRate": 0.0, "questionRate": 0.015384615384615385, "accent": false, "saturation": 2.2487046632124352, "paragraphNum": 0, "nounNum": 213, "verbNum": 175, "adjNum": 83, "infNum": 16, "partPastNum": 1, "partPresNum": 8, "partFutNum": 0, "transNum": 0, "xNum": 64, "advNum": 67, "properNounNum": 49, "numNum": 20, "conjNum": 85, "punctNum": 239, "pronNum": 80, "relPronNum": 17, "demPronNum": 50, "adposNum": 9, "multiplePunctNum": 59, "phraseNum": 0, "nounRate": 0.17929292929292928, "verbRate": 0.1473063973063973, "adjRate": 0.06986531986531987, "infRate": 0.013468013468013467, "partPastRate": 0.0008417508417508417, "partPresRate": 0.006734006734006734, "partFutRate": 0.0, "transRate": 0.0, "xRate": 0.05387205387205387, "advRate": 0.0563973063973064, "properNounRate": 0.041245791245791245, "numRate": 0.016835016835016835, "conjRate": 0.07154882154882154, "punctRate": 0.20117845117845118, "pronRate": 0.06734006734006734, "relPronRate": 0.01430976430976431, "demPronRate": 0.04208754208754209, "adposRate": 0.007575757575757576, "multiplePunctRate": 0.24686192468619247, "partsDensityRate": 2.7823834196891193, "contentfulness": 8.261538461538462, "phraseRate": 0.0, "pastTenseNum": 81, "presentTenseNum": 79, "condNum": 2, "impNum": 7, "freqNum": 0, "causNum": 1, "modalNum": 4, "sg1VerbNum": 37, "sg2VerbNum": 12, "sg3VerbNum": 178, "pl1VerbNum": 6, "pl2VerbNum": 2, "pl3VerbNum": 19, "superlatNum": 1, "comparatNum": 5, "specDerivSuffixNum": 0, "pluralNounNum": 15, "pastTenseRate": 0.46285714285714286, "presentTenseRate": 0.4514285714285714, "condRate": 0.011428571428571429, "impRate": 0.04, "freqRate": 0.0, "causRate": 0.005714285714285714, "modalRate": 0.022857142857142857, "sg1VerbRate": 0.21142857142857144, "sg2VerbRate": 0.06857142857142857, "sg3VerbRate": 1.0171428571428571, "pl1VerbRate": 0.03428571428571429, "pl2VerbRate": 0.011428571428571429, "pl3VerbRate": 0.10857142857142857, "superlatRate": 0.012048192771084338, "comparatRate": 0.060240963855421686, "specDerivSuffixRate": 0.0, "pluralNounRate": 0.07042253521126761, "subjNum": 84, "objNum": 52, "attNum": 49, "subordNum": 73, "adverbNum": 94, "coordNum": 34, "clauseNum": 193, "simpleNum": 11, "complexNum": 54, "complexity1Num": 21, "complexity2Num": 11, "complexity3Num": 11, "compoundNum": 0, "subjRate": 0.0707070707070707, "objRate": 0.04377104377104377, "attRate": 0.041245791245791245, "subordRate": 0.061447811447811446, "adverbRate": 0.07912457912457913, "coordRate": 0.02861952861952862, "partsRate": 1.621761658031088, "clauseRate": 2.9692307692307693, "simpleRate": 0.16923076923076924, "complexRate": 0.8307692307692308, "complexity1Rate": 0.3230769230769231, "complexity2Rate": 0.16923076923076924, "complexity3Rate": 0.16923076923076924, "complexClauseRate": 3.3703703703703702, "sentencesPerParagraph": 0.0, "wordsLengthRate": 5.317175974710222, "compoundRate": 0.0, "positiveNum": 0, "negativeNum": 0, "precoPositiveNum": 0, "precoNegativeNum": 0, "negemoNum": 0, "negationNum": 9, "functionNum": 651, "contentNum": 537, "vulgarNum": 0, "racistNum": 0, "specStyleNum": 0, "addressingNum": 0, "closingNum": 0, "postscriptNum": 0, "brutalNum": 0, "positiveRate": 0.0, "negativeRate": 0.0, "precoPositiveRate": 0.0, "precoNegativeRate": 0.0, "negemoRate": 0.0, "negationRate": 0.007575757575757576, "functionRate": 0.547979797979798, "contentRate": 0.45202020202020204, "vulgarRate": 0.0, "racistRate": 0.0, "specStyleRate": 0.0, "addressingRate": 0.0, "closingRate": 0.0, "postscriptRate": 0.0, "brutalRate": 0.0, "epistemicNum": 0, "investNum": 0, "conditionNum": 0, "weaselNum": 0, "peacockNum": 0, "hedgeNum": 0, "doxasticNum": 0, "epistemicRate": 0.0, "investRate": 0.0, "conditionRate": 0.0, "weaselRate": 0.0, "peacockRate": 0.0, "hedgeRate": 0.0, "doxasticRate": 0.0, "loveNum": 0, "anxietyNum": 0, "sorrowNum": 0, "joyNum": 0, "disgustNum": 0, "fearNum": 0, "surpriseNum": 0, "angerNum": 0, "loveRate": 0.0, "anxietyRate": 0.0, "sorrowRate": 0.0, "joyRate": 0.0, "disgustRate": 0.0, "fearRate": 0.0, "surpriseRate": 0.0, "angerRate": 0.0, "slangBeGeneralNum": 0, "slangBeCigaretteNum": 0, "slangBeHumanNum": 0, "slangBeVehicleNum": 0, "slangBeDrugNum": 0, "slangBvNum": 0, "slangBeGeneralRate": 0.0, "slangBeCigaretteRate": 0.0, "slangBeHumanRate": 0.0, "slangBeVehicleRate": 0.0, "slangBeDrugRate": 0.0, "slangBvRate": 0.0, "speechactNum": 0, "quoteNum": 0, "dashNum": 0, "publicNum": 0, "privateNum": 0, "suasiveNum": 0, "discMarkerNum": 0, "smileyNum": 0, "dateNum": 0, "hesitationNum": 0, "restartNum": 1, "repeatNum": 1, "conjBeforeDiscNum": 0, "conjAfterDiscNum": 0, "wordBeforeHesitationNum": 0, "wordAfterHesitationNum": 0, "otherCollocationNum": 0, "speechactRate": 0.0, "quoteRate": 0.0, "dashRate": 0.0, "publicRate": 0.0, "privateRate": 0.0, "suasiveRate": 0.0, "discMarkerRate": 0.0, "smileyRate": 0.0, "dateRate": 0.0, "hesitationRate": 0.0, "restartRate": 0.0008417508417508417, "repeatRate": 0.0008417508417508417, "conjBeforeDiscRate": 0.0, "conjAfterDiscRate": 0.0, "wordBeforeHesitationRate": 0.0, "wordAfterHesitationRate": 0.0, "otherCollocationRate": 0.0, "easyWordNum": 1095, "hardWordNum": 93, "easyWordRate": 0.9217171717171717, "hardWordRate": 0.07828282828282829, "fleschReadingEaseScore": 66.93846853146856, "gunningFogIndex": 7.341745661745661, "fleschKincaidGradeLevel": 8.463252525252525, "colemanLiauIndex": 10.38752946127946, "smogIndex": 9.962388103665196, "automatedReadabilityIndex": 8.649724164724166, "linsearWriteIndex": -0.1504791504791504, "author": "", "locationNameNum": 15, "locationNameRate": 0.012626262626262626, "personNameNum": 18, "personNameRate": 0.015151515151515152, "organizationNameNum": 0, "organizationNameRate": 0.0, "misspelledNum": 307, "misspelledRate": 0.25841750841750843, "missingAccentNum": 300, "missingAccentRate": 0.25252525252525254, "foreignAccentNum": 0, "foreignAccentRate": 0.0, "wordConcatNum": 1, "wordConcatRate": 0.0008417508417508417, "jLyMistakeNum": 0, "jLyMistakeRate": 0.0, "freqSuffixNum": 0, "partsNum": 313, "privateVNum": 0, "publicVNum": 0, "clauseWordNum": 193}