{"tokenNum": 1042, "sentenceNum": 50, "lemmaNum": 438, "lemmaRate": 0.42034548944337813, "sentenceLength": 20.84, "allUpperNum": 2, "firstUpperNum": 74, "allUpperRate": 0.0019193857965451055, "firstUpperRate": 0.0710172744721689, "declarSentNum": 49, "imperSentNum": 1, "questionNum": 0, "declarSentRate": 0.98, "imperSentRate": 0.02, "questionRate": 0.0, "accent": true, "saturation": 3.4761904761904763, "paragraphNum": 0, "nounNum": 230, "verbNum": 111, "adjNum": 136, "infNum": 8, "partPastNum": 8, "partPresNum": 16, "partFutNum": 0, "transNum": 3, "xNum": 52, "advNum": 85, "properNounNum": 19, "numNum": 5, "conjNum": 54, "punctNum": 158, "pronNum": 65, "relPronNum": 16, "demPronNum": 36, "adposNum": 23, "multiplePunctNum": 3, "phraseNum": 0, "nounRate": 0.22072936660268713, "verbRate": 0.10652591170825336, "adjRate": 0.13051823416506717, "infRate": 0.007677543186180422, "partPastRate": 0.007677543186180422, "partPresRate": 0.015355086372360844, "partFutRate": 0.0, "transRate": 0.0028790786948176585, "xRate": 0.04990403071017274, "advRate": 0.08157389635316699, "properNounRate": 0.018234165067178502, "numRate": 0.0047984644913627635, "conjRate": 0.05182341650671785, "punctRate": 0.15163147792706333, "pronRate": 0.06238003838771593, "relPronRate": 0.015355086372360844, "demPronRate": 0.0345489443378119, "adposRate": 0.022072936660268713, "multiplePunctRate": 0.0189873417721519, "partsDensityRate": 4.4603174603174605, "contentfulness": 11.24, "phraseRate": 0.0, "pastTenseNum": 27, "presentTenseNum": 77, "condNum": 6, "impNum": 21, "freqNum": 0, "causNum": 0, "modalNum": 1, "sg1VerbNum": 16, "sg2VerbNum": 17, "sg3VerbNum": 111, "pl1VerbNum": 2, "pl2VerbNum": 0, "pl3VerbNum": 29, "superlatNum": 0, "comparatNum": 2, "specDerivSuffixNum": 0, "pluralNounNum": 40, "pastTenseRate": 0.24324324324324326, "presentTenseRate": 0.6936936936936937, "condRate": 0.05405405405405406, "impRate": 0.1891891891891892, "freqRate": 0.0, "causRate": 0.0, "modalRate": 0.009009009009009009, "sg1VerbRate": 0.14414414414414414, "sg2VerbRate": 0.15315315315315314, "sg3VerbRate": 1.0, "pl1VerbRate": 0.018018018018018018, "pl2VerbRate": 0.0, "pl3VerbRate": 0.26126126126126126, "superlatRate": 0.0, "comparatRate": 0.014705882352941176, "specDerivSuffixRate": 0.0, "pluralNounRate": 0.17391304347826086, "subjNum": 67, "objNum": 56, "attNum": 96, "subordNum": 39, "adverbNum": 105, "coordNum": 44, "clauseNum": 126, "simpleNum": 12, "complexNum": 38, "complexity1Num": 21, "complexity2Num": 6, "complexity3Num": 5, "compoundNum": 0, "subjRate": 0.06429942418426103, "objRate": 0.053742802303262956, "attRate": 0.09213051823416507, "subordRate": 0.03742802303262956, "adverbRate": 0.10076775431861804, "coordRate": 0.04222648752399232, "partsRate": 2.9206349206349205, "clauseRate": 2.52, "simpleRate": 0.24, "complexRate": 0.76, "complexity1Rate": 0.42, "complexity2Rate": 0.12, "complexity3Rate": 0.1, "complexClauseRate": 3.0, "sentencesPerParagraph": 0.0, "wordsLengthRate": 5.54524886877828, "compoundRate": 0.0, "positiveNum": 0, "negativeNum": 0, "precoPositiveNum": 0, "precoNegativeNum": 0, "negemoNum": 0, "negationNum": 17, "functionNum": 480, "contentNum": 562, "vulgarNum": 0, "racistNum": 0, "specStyleNum": 0, "addressingNum": 0, "closingNum": 0, "postscriptNum": 0, "brutalNum": 0, "positiveRate": 0.0, "negativeRate": 0.0, "precoPositiveRate": 0.0, "precoNegativeRate": 0.0, "negemoRate": 0.0, "negationRate": 0.016314779270633396, "functionRate": 0.46065259117082535, "contentRate": 0.5393474088291746, "vulgarRate": 0.0, "racistRate": 0.0, "specStyleRate": 0.0, "addressingRate": 0.0, "closingRate": 0.0, "postscriptRate": 0.0, "brutalRate": 0.0, "epistemicNum": 0, "investNum": 0, "conditionNum": 0, "weaselNum": 0, "peacockNum": 0, "hedgeNum": 0, "doxasticNum": 0, "epistemicRate": 0.0, "investRate": 0.0, "conditionRate": 0.0, "weaselRate": 0.0, "peacockRate": 0.0, "hedgeRate": 0.0, "doxasticRate": 0.0, "loveNum": 0, "anxietyNum": 0, "sorrowNum": 0, "joyNum": 0, "disgustNum": 0, "fearNum": 0, "surpriseNum": 0, "angerNum": 0, "loveRate": 0.0, "anxietyRate": 0.0, "sorrowRate": 0.0, "joyRate": 0.0, "disgustRate": 0.0, "fearRate": 0.0, "surpriseRate": 0.0, "angerRate": 0.0, "slangBeGeneralNum": 0, "slangBeCigaretteNum": 0, "slangBeHumanNum": 0, "slangBeVehicleNum": 0, "slangBeDrugNum": 0, "slangBvNum": 0, "slangBeGeneralRate": 0.0, "slangBeCigaretteRate": 0.0, "slangBeHumanRate": 0.0, "slangBeVehicleRate": 0.0, "slangBeDrugRate": 0.0, "slangBvRate": 0.0, "speechactNum": 0, "quoteNum": 0, "dashNum": 0, "publicNum": 0, "privateNum": 0, "suasiveNum": 0, "discMarkerNum": 0, "smileyNum": 0, "dateNum": 0, "hesitationNum": 0, "restartNum": 0, "repeatNum": 0, "conjBeforeDiscNum": 0, "conjAfterDiscNum": 0, "wordBeforeHesitationNum": 0, "wordAfterHesitationNum": 0, "otherCollocationNum": 0, "speechactRate": 0.0, "quoteRate": 0.0, "dashRate": 0.0, "publicRate": 0.0, "privateRate": 0.0, "suasiveRate": 0.0, "discMarkerRate": 0.0, "smileyRate": 0.0, "dateRate": 0.0, "hesitationRate": 0.0, "restartRate": 0.0, "repeatRate": 0.0, "conjBeforeDiscRate": 0.0, "conjAfterDiscRate": 0.0, "wordBeforeHesitationRate": 0.0, "wordAfterHesitationRate": 0.0, "otherCollocationRate": 0.0, "easyWordNum": 943, "hardWordNum": 99, "easyWordRate": 0.9049904030710173, "hardWordRate": 0.09500959692898273, "fleschReadingEaseScore": 52.693148560460656, "gunningFogIndex": 8.374003838771593, "fleschKincaidGradeLevel": 11.086928214971213, "colemanLiauIndex": 12.47976967370441, "smogIndex": 11.167646547728637, "automatedReadabilityIndex": 11.604328214971211, "linsearWriteIndex": 0.14011516314779282, "author": "", "locationNameNum": 4, "locationNameRate": 0.003838771593090211, "personNameNum": 6, "personNameRate": 0.005758157389635317, "organizationNameNum": 1, "organizationNameRate": 0.0009596928982725527, "misspelledNum": 26, "misspelledRate": 0.02495201535508637, "missingAccentNum": 7, "missingAccentRate": 0.0067178502879078695, "foreignAccentNum": 0, "foreignAccentRate": 0.0, "wordConcatNum": 2, "wordConcatRate": 0.0019193857965451055, "jLyMistakeNum": 0, "jLyMistakeRate": 0.0, "freqSuffixNum": 0, "partsNum": 368, "privateVNum": 0, "publicVNum": 0, "clauseWordNum": 126}