{"tokenNum": 461, "sentenceNum": 24, "lemmaNum": 196, "lemmaRate": 0.42516268980477223, "sentenceLength": 19.208333333333332, "allUpperNum": 1, "firstUpperNum": 32, "allUpperRate": 0.0021691973969631237, "firstUpperRate": 0.06941431670281996, "declarSentNum": 24, "imperSentNum": 0, "questionNum": 0, "declarSentRate": 1.0, "imperSentRate": 0.0, "questionRate": 0.0, "accent": true, "saturation": 2.925373134328358, "paragraphNum": 0, "nounNum": 75, "verbNum": 63, "adjNum": 28, "infNum": 12, "partPastNum": 0, "partPresNum": 0, "partFutNum": 0, "transNum": 1, "xNum": 23, "advNum": 56, "properNounNum": 6, "numNum": 5, "conjNum": 44, "punctNum": 81, "pronNum": 35, "relPronNum": 6, "demPronNum": 27, "adposNum": 5, "multiplePunctNum": 0, "phraseNum": 0, "nounRate": 0.16268980477223427, "verbRate": 0.13665943600867678, "adjRate": 0.06073752711496746, "infRate": 0.026030368763557483, "partPastRate": 0.0, "partPresRate": 0.0, "partFutRate": 0.0, "transRate": 0.0021691973969631237, "xRate": 0.049891540130151846, "advRate": 0.12147505422993492, "properNounRate": 0.013015184381778741, "numRate": 0.010845986984815618, "conjRate": 0.09544468546637744, "punctRate": 0.175704989154013, "pronRate": 0.07592190889370933, "relPronRate": 0.013015184381778741, "demPronRate": 0.05856832971800434, "adposRate": 0.010845986984815618, "multiplePunctRate": 0.0, "partsDensityRate": 3.3134328358208953, "contentfulness": 9.25, "phraseRate": 0.0, "pastTenseNum": 8, "presentTenseNum": 43, "condNum": 6, "impNum": 3, "freqNum": 0, "causNum": 0, "modalNum": 5, "sg1VerbNum": 7, "sg2VerbNum": 1, "sg3VerbNum": 68, "pl1VerbNum": 3, "pl2VerbNum": 0, "pl3VerbNum": 9, "superlatNum": 2, "comparatNum": 1, "specDerivSuffixNum": 0, "pluralNounNum": 11, "pastTenseRate": 0.12698412698412698, "presentTenseRate": 0.6825396825396826, "condRate": 0.09523809523809523, "impRate": 0.047619047619047616, "freqRate": 0.0, "causRate": 0.0, "modalRate": 0.07936507936507936, "sg1VerbRate": 0.1111111111111111, "sg2VerbRate": 0.015873015873015872, "sg3VerbRate": 1.0793650793650793, "pl1VerbRate": 0.047619047619047616, "pl2VerbRate": 0.0, "pl3VerbRate": 0.14285714285714285, "superlatRate": 0.07142857142857142, "comparatRate": 0.03571428571428571, "specDerivSuffixRate": 0.0, "pluralNounRate": 0.14666666666666667, "subjNum": 37, "objNum": 22, "attNum": 16, "subordNum": 26, "adverbNum": 72, "coordNum": 18, "clauseNum": 67, "simpleNum": 4, "complexNum": 20, "complexity1Num": 9, "complexity2Num": 5, "complexity3Num": 2, "compoundNum": 0, "subjRate": 0.08026030368763558, "objRate": 0.04772234273318872, "attRate": 0.03470715835140998, "subordRate": 0.05639913232104121, "adverbRate": 0.1561822125813449, "coordRate": 0.039045553145336226, "partsRate": 2.462686567164179, "clauseRate": 2.7916666666666665, "simpleRate": 0.16666666666666666, "complexRate": 0.8333333333333334, "complexity1Rate": 0.375, "complexity2Rate": 0.20833333333333334, "complexity3Rate": 0.08333333333333333, "complexClauseRate": 3.15, "sentencesPerParagraph": 0.0, "wordsLengthRate": 4.886842105263158, "compoundRate": 0.0, "positiveNum": 0, "negativeNum": 0, "precoPositiveNum": 0, "precoNegativeNum": 0, "negemoNum": 0, "negationNum": 13, "functionNum": 239, "contentNum": 222, "vulgarNum": 0, "racistNum": 0, "specStyleNum": 0, "addressingNum": 0, "closingNum": 0, "postscriptNum": 0, "brutalNum": 0, "positiveRate": 0.0, "negativeRate": 0.0, "precoPositiveRate": 0.0, "precoNegativeRate": 0.0, "negemoRate": 0.0, "negationRate": 0.028199566160520606, "functionRate": 0.5184381778741866, "contentRate": 0.48156182212581344, "vulgarRate": 0.0, "racistRate": 0.0, "specStyleRate": 0.0, "addressingRate": 0.0, "closingRate": 0.0, "postscriptRate": 0.0, "brutalRate": 0.0, "epistemicNum": 0, "investNum": 0, "conditionNum": 0, "weaselNum": 0, "peacockNum": 0, "hedgeNum": 0, "doxasticNum": 0, "epistemicRate": 0.0, "investRate": 0.0, "conditionRate": 0.0, "weaselRate": 0.0, "peacockRate": 0.0, "hedgeRate": 0.0, "doxasticRate": 0.0, "loveNum": 0, "anxietyNum": 0, "sorrowNum": 0, "joyNum": 0, "disgustNum": 0, "fearNum": 0, "surpriseNum": 0, "angerNum": 0, "loveRate": 0.0, "anxietyRate": 0.0, "sorrowRate": 0.0, "joyRate": 0.0, "disgustRate": 0.0, "fearRate": 0.0, "surpriseRate": 0.0, "angerRate": 0.0, "slangBeGeneralNum": 0, "slangBeCigaretteNum": 0, "slangBeHumanNum": 0, "slangBeVehicleNum": 0, "slangBeDrugNum": 0, "slangBvNum": 0, "slangBeGeneralRate": 0.0, "slangBeCigaretteRate": 0.0, "slangBeHumanRate": 0.0, "slangBeVehicleRate": 0.0, "slangBeDrugRate": 0.0, "slangBvRate": 0.0, "speechactNum": 0, "quoteNum": 0, "dashNum": 0, "publicNum": 0, "privateNum": 0, "suasiveNum": 0, "discMarkerNum": 0, "smileyNum": 0, "dateNum": 0, "hesitationNum": 0, "restartNum": 0, "repeatNum": 0, "conjBeforeDiscNum": 0, "conjAfterDiscNum": 0, "wordBeforeHesitationNum": 0, "wordAfterHesitationNum": 0, "otherCollocationNum": 0, "speechactRate": 0.0, "quoteRate": 0.0, "dashRate": 0.0, "publicRate": 0.0, "privateRate": 0.0, "suasiveRate": 0.0, "discMarkerRate": 0.0, "smileyRate": 0.0, "dateRate": 0.0, "hesitationRate": 0.0, "restartRate": 0.0, "repeatRate": 0.0, "conjBeforeDiscRate": 0.0, "conjAfterDiscRate": 0.0, "wordBeforeHesitationRate": 0.0, "wordAfterHesitationRate": 0.0, "otherCollocationRate": 0.0, "easyWordNum": 441, "hardWordNum": 20, "easyWordRate": 0.9566160520607375, "hardWordRate": 0.04338394793926247, "fleschReadingEaseScore": 75.21142669920465, "gunningFogIndex": 7.700686912509038, "fleschKincaidGradeLevel": 7.54072939262473, "colemanLiauIndex": 8.628650759219088, "smogIndex": 7.793537801064561, "automatedReadabilityIndex": 7.708917208966014, "linsearWriteIndex": 1.1601590744757773, "author": "", "locationNameNum": 0, "locationNameRate": 0.0, "personNameNum": 1, "personNameRate": 0.0021691973969631237, "organizationNameNum": 3, "organizationNameRate": 0.006507592190889371, "misspelledNum": 2, "misspelledRate": 0.004338394793926247, "missingAccentNum": 1, "missingAccentRate": 0.0021691973969631237, "foreignAccentNum": 0, "foreignAccentRate": 0.0, "wordConcatNum": 0, "wordConcatRate": 0.0, "jLyMistakeNum": 0, "jLyMistakeRate": 0.0, "freqSuffixNum": 0, "partsNum": 165, "privateVNum": 0, "publicVNum": 0, "clauseWordNum": 67}