{"tokenNum": 378, "sentenceNum": 25, "lemmaNum": 208, "lemmaRate": 0.5502645502645502, "sentenceLength": 15.12, "allUpperNum": 1, "firstUpperNum": 44, "allUpperRate": 0.0026455026455026454, "firstUpperRate": 0.1164021164021164, "declarSentNum": 25, "imperSentNum": 0, "questionNum": 0, "declarSentRate": 1.0, "imperSentRate": 0.0, "questionRate": 0.0, "accent": false, "saturation": 4.425531914893617, "paragraphNum": 0, "nounNum": 59, "verbNum": 73, "adjNum": 21, "infNum": 16, "partPastNum": 0, "partPresNum": 3, "partFutNum": 0, "transNum": 1, "xNum": 27, "advNum": 52, "properNounNum": 18, "numNum": 0, "conjNum": 32, "punctNum": 30, "pronNum": 44, "relPronNum": 9, "demPronNum": 21, "adposNum": 1, "multiplePunctNum": 0, "phraseNum": 0, "nounRate": 0.15608465608465608, "verbRate": 0.1931216931216931, "adjRate": 0.05555555555555555, "infRate": 0.042328042328042326, "partPastRate": 0.0, "partPresRate": 0.007936507936507936, "partFutRate": 0.0, "transRate": 0.0026455026455026454, "xRate": 0.07142857142857142, "advRate": 0.13756613756613756, "properNounRate": 0.047619047619047616, "numRate": 0.0, "conjRate": 0.08465608465608465, "punctRate": 0.07936507936507936, "pronRate": 0.1164021164021164, "relPronRate": 0.023809523809523808, "demPronRate": 0.05555555555555555, "adposRate": 0.0026455026455026454, "multiplePunctRate": 0.0, "partsDensityRate": 4.361702127659575, "contentfulness": 8.2, "phraseRate": 0.0, "pastTenseNum": 10, "presentTenseNum": 47, "condNum": 0, "impNum": 8, "freqNum": 0, "causNum": 0, "modalNum": 1, "sg1VerbNum": 34, "sg2VerbNum": 7, "sg3VerbNum": 55, "pl1VerbNum": 3, "pl2VerbNum": 1, "pl3VerbNum": 4, "superlatNum": 0, "comparatNum": 2, "specDerivSuffixNum": 0, "pluralNounNum": 6, "pastTenseRate": 0.136986301369863, "presentTenseRate": 0.6438356164383562, "condRate": 0.0, "impRate": 0.1095890410958904, "freqRate": 0.0, "causRate": 0.0, "modalRate": 0.0136986301369863, "sg1VerbRate": 0.4657534246575342, "sg2VerbRate": 0.0958904109589041, "sg3VerbRate": 0.7534246575342466, "pl1VerbRate": 0.0410958904109589, "pl2VerbRate": 0.0136986301369863, "pl3VerbRate": 0.0547945205479452, "superlatRate": 0.0, "comparatRate": 0.09523809523809523, "specDerivSuffixRate": 0.0, "pluralNounRate": 0.1016949152542373, "subjNum": 30, "objNum": 27, "attNum": 9, "subordNum": 21, "adverbNum": 74, "coordNum": 16, "clauseNum": 47, "simpleNum": 10, "complexNum": 15, "complexity1Num": 8, "complexity2Num": 7, "complexity3Num": 0, "compoundNum": 0, "subjRate": 0.07936507936507936, "objRate": 0.07142857142857142, "attRate": 0.023809523809523808, "subordRate": 0.05555555555555555, "adverbRate": 0.19576719576719576, "coordRate": 0.042328042328042326, "partsRate": 3.3191489361702127, "clauseRate": 1.88, "simpleRate": 0.4, "complexRate": 0.6, "complexity1Rate": 0.32, "complexity2Rate": 0.28, "complexity3Rate": 0.0, "complexClauseRate": 2.466666666666667, "sentencesPerParagraph": 0.0, "wordsLengthRate": 5.183908045977011, "compoundRate": 0.0, "positiveNum": 0, "negativeNum": 0, "precoPositiveNum": 0, "precoNegativeNum": 0, "negemoNum": 0, "negationNum": 18, "functionNum": 173, "contentNum": 205, "vulgarNum": 0, "racistNum": 0, "specStyleNum": 0, "addressingNum": 0, "closingNum": 0, "postscriptNum": 0, "brutalNum": 0, "positiveRate": 0.0, "negativeRate": 0.0, "precoPositiveRate": 0.0, "precoNegativeRate": 0.0, "negemoRate": 0.0, "negationRate": 0.047619047619047616, "functionRate": 0.4576719576719577, "contentRate": 0.5423280423280423, "vulgarRate": 0.0, "racistRate": 0.0, "specStyleRate": 0.0, "addressingRate": 0.0, "closingRate": 0.0, "postscriptRate": 0.0, "brutalRate": 0.0, "epistemicNum": 0, "investNum": 0, "conditionNum": 0, "weaselNum": 0, "peacockNum": 0, "hedgeNum": 0, "doxasticNum": 0, "epistemicRate": 0.0, "investRate": 0.0, "conditionRate": 0.0, "weaselRate": 0.0, "peacockRate": 0.0, "hedgeRate": 0.0, "doxasticRate": 0.0, "loveNum": 0, "anxietyNum": 0, "sorrowNum": 0, "joyNum": 0, "disgustNum": 0, "fearNum": 0, "surpriseNum": 0, "angerNum": 0, "loveRate": 0.0, "anxietyRate": 0.0, "sorrowRate": 0.0, "joyRate": 0.0, "disgustRate": 0.0, "fearRate": 0.0, "surpriseRate": 0.0, "angerRate": 0.0, "slangBeGeneralNum": 0, "slangBeCigaretteNum": 0, "slangBeHumanNum": 0, "slangBeVehicleNum": 0, "slangBeDrugNum": 0, "slangBvNum": 0, "slangBeGeneralRate": 0.0, "slangBeCigaretteRate": 0.0, "slangBeHumanRate": 0.0, "slangBeVehicleRate": 0.0, "slangBeDrugRate": 0.0, "slangBvRate": 0.0, "speechactNum": 0, "quoteNum": 0, "dashNum": 0, "publicNum": 0, "privateNum": 0, "suasiveNum": 0, "discMarkerNum": 0, "smileyNum": 0, "dateNum": 0, "hesitationNum": 0, "restartNum": 0, "repeatNum": 1, "conjBeforeDiscNum": 0, "conjAfterDiscNum": 0, "wordBeforeHesitationNum": 0, "wordAfterHesitationNum": 0, "otherCollocationNum": 0, "speechactRate": 0.0, "quoteRate": 0.0, "dashRate": 0.0, "publicRate": 0.0, "privateRate": 0.0, "suasiveRate": 0.0, "discMarkerRate": 0.0, "smileyRate": 0.0, "dateRate": 0.0, "hesitationRate": 0.0, "restartRate": 0.0, "repeatRate": 0.0026455026455026454, "conjBeforeDiscRate": 0.0, "conjAfterDiscRate": 0.0, "wordBeforeHesitationRate": 0.0, "wordAfterHesitationRate": 0.0, "otherCollocationRate": 0.0, "easyWordNum": 344, "hardWordNum": 34, "easyWordRate": 0.91005291005291, "hardWordRate": 0.08994708994708994, "fleschReadingEaseScore": 56.754866666666686, "gunningFogIndex": 6.0839788359788365, "fleschKincaidGradeLevel": 9.099392592592594, "colemanLiauIndex": 12.340912698412694, "smogIndex": 9.210782826323648, "automatedReadabilityIndex": 8.633333333333333, "linsearWriteIndex": 1.2328042328042326, "author": "", "locationNameNum": 0, "locationNameRate": 0.0, "personNameNum": 6, "personNameRate": 0.015873015873015872, "organizationNameNum": 1, "organizationNameRate": 0.0026455026455026454, "misspelledNum": 99, "misspelledRate": 0.2619047619047619, "missingAccentNum": 87, "missingAccentRate": 0.23015873015873015, "foreignAccentNum": 0, "foreignAccentRate": 0.0, "wordConcatNum": 3, "wordConcatRate": 0.007936507936507936, "jLyMistakeNum": 0, "jLyMistakeRate": 0.0, "freqSuffixNum": 0, "partsNum": 156, "privateVNum": 0, "publicVNum": 0, "clauseWordNum": 47}